openrelik_ai_common/__init__.py
openrelik_ai_common/providers/__init__.py
openrelik_ai_common/providers/config.py
openrelik_ai_common/providers/googleai.py
openrelik_ai_common/providers/interface.py
openrelik_ai_common/providers/manager.py
openrelik_ai_common/providers/ollama.py
openrelik_ai_common/providers/vertexai.py
openrelik_ai_common/utils/__init__.py
openrelik_ai_common/utils/prompt.py
openrelik_ai_common-2024.10.21.dist-info/LICENSE
openrelik_ai_common-2024.10.21.dist-info/METADATA
openrelik_ai_common-2024.10.21.dist-info/WHEEL
openrelik_ai_common-2024.10.21.dist-info/RECORD
